Namespace/Namespace.py
Namespace/__init__.py
javascript_namespaces-1.4.1.dist-info/METADATA
javascript_namespaces-1.4.1.dist-info/WHEEL
javascript_namespaces-1.4.1.dist-info/top_level.txt
javascript_namespaces-1.4.1.dist-info/RECORD
