Metadata-Version: 2.1
Name: javascript-namespaces
Version: 1.4.1
Summary: Namespace
Home-page: https://github.com/Jakub21/Namespace
Author: Jakub21
License: MIT
